{"legislative_session": "20252026", "identifier": "AB1730", "title": "Community colleges: gender equity: report.", "from_organization": "~{\"classification\": \"lower\"}", "classification": ["bill"], "subject": ["Communitycolleges", "genderequity", "report"], "abstracts": [{"note": "summary", "abstract": "Existing law establishes the California Community Colleges, under the administration of the Board of Governors of the California Community Colleges, as one of the segments of public postsecondary education in the state. The board of governors appoints the Chancellor of the California Community Colleges to serve as the chief executive officer of the segment. Existing law requires the chancellor, on or before December 1, 2025, and in consultation with stakeholders, to submit a report to the Legislature with recommendations for establishing systemic campus reforms that effectively prevent, detect, and address sexual harassment on community college campuses, as provided. \n\nThis bill would state the intent of the Legislature to enact in subsequent legislation some of the recommendations from the above-described report."}], "other_titles": [], "other_identifiers": [], "actions": [{"description": "Read first time. To print.", "date": "2026-02-05", "organization_id": "~{\"classification\": \"lower\"}", "classification": ["reading-1"], "related_entities": []}, {"description": "From printer. May be heard in committee March 8.", "date": "2026-02-06", "organization_id": "~{\"classification\": \"lower\"}", "classification": [], "related_entities": []}], "sponsorships": [{"name": "Fong", "classification": "author", "entity_type": "person", "primary": true, "person_id": "~{\"name\": \"Fong\"}", "organization_id": null}], "related_bills": [], "versions": [{"note": "AB1730", "links": [{"url": "http://leginfo.legislature.ca.gov/faces/billNavClient.xhtml?bill_id=202520260AB1730", "media_type": "text/html"}], "date": "", "classification": ""}, {"note": "02/05/26 - Introduced", "links": [{"url": "https://leginfo.legislature.ca.gov/faces/billPdf.xhtml?bill_id=202520260AB1730&version=20250AB173099INT", "media_type": "application/pdf"}], "date": "2026-02-05", "classification": ""}], "documents": [], "citations": [], "sources": [{"url": "http://leginfo.legislature.ca.gov/faces/billNavClient.xhtml?bill_id=202520260AB1730", "note": ""}], "extras": {"impact_clause": "An act relating to community colleges.", "tags": []}, "jurisdiction": {"id": "ocd-jurisdiction/country:us/state:ca/government", "name": "California", "classification": "state", "division_id": "ocd-division/country:us/state:ca"}, "scraped_at": "2026-02-16T09:02:16+00:00", "_id": "311864b6-0b16-11f1-8107-d26818b831da"}