{"legislative_session": "20252026", "identifier": "AB2729", "title": "Medi-Cal: employer penalty: contribution.", "from_organization": "~{\"classification\": \"lower\"}", "classification": ["bill"], "subject": ["Medi-Cal", "contribution", "employerpenalty"], "abstracts": [{"note": "summary", "abstract": "Existing law establishes the Medi-Cal program, which is administered by the State Department of Health Care Services and under which qualified low-income individuals receive health care services. The Medi-Cal program is in part governed by, and funded pursuant to, federal Medicaid program provisions.\n\nExisting law, the federal Patient Protection and Affordable Care Act, imposes a certain assessment on an applicable large employer, as defined, that offers full-time employees and their dependents the opportunity to enroll in minimum essential coverage, and for whom one or more full-time employees have been certified as having enrolled in a qualified health plan for which a premium tax credit or cost-sharing reduction is allowed or paid.\n\nThis bill would state the intent of the Legislature to enact legislation that would require employers that employ individuals who are enrolled in the Medi-Cal program to pay a penalty as a contribution to a Medi-Cal fund."}], "other_titles": [], "other_identifiers": [], "actions": [{"description": "Read first time. To print.", "date": "2026-02-20", "organization_id": "~{\"classification\": \"lower\"}", "classification": ["reading-1"], "related_entities": []}], "sponsorships": [{"name": "Bonta", "classification": "author", "entity_type": "person", "primary": true, "person_id": "~{\"name\": \"Bonta\"}", "organization_id": null}, {"name": "Addis", "classification": "coauthor", "entity_type": "person", "primary": false, "person_id": "~{\"name\": \"Addis\"}", "organization_id": null}, {"name": "Ahrens", "classification": "coauthor", "entity_type": "person", "primary": false, "person_id": "~{\"name\": \"Ahrens\"}", "organization_id": null}, {"name": "Arambula", "classification": "coauthor", "entity_type": "person", "primary": false, "person_id": "~{\"name\": \"Arambula\"}", "organization_id": null}, {"name": "Bryan", "classification": "coauthor", "entity_type": "person", "primary": false, "person_id": "~{\"name\": \"Bryan\"}", "organization_id": null}, {"name": "Elhawary", "classification": "coauthor", "entity_type": "person", "primary": false, "person_id": "~{\"name\": \"Elhawary\"}", "organization_id": null}, {"name": "Garcia", "classification": "coauthor", "entity_type": "person", "primary": false, "person_id": "~{\"name\": \"Garcia\"}", "organization_id": null}, {"name": "Haney", "classification": "coauthor", "entity_type": "person", "primary": false, "person_id": "~{\"name\": \"Haney\"}", "organization_id": null}, {"name": "Jackson", "classification": "coauthor", "entity_type": "person", "primary": false, "person_id": "~{\"name\": \"Jackson\"}", "organization_id": null}, {"name": "Kalra", "classification": "coauthor", "entity_type": "person", "primary": false, "person_id": "~{\"name\": \"Kalra\"}", "organization_id": null}, {"name": "Lee", "classification": "coauthor", "entity_type": "person", "primary": false, "person_id": "~{\"name\": \"Lee\"}", "organization_id": null}, {"name": "McKinnor", "classification": "coauthor", "entity_type": "person", "primary": false, "person_id": "~{\"name\": \"McKinnor\"}", "organization_id": null}, {"name": "Ortega", "classification": "coauthor", "entity_type": "person", "primary": false, "person_id": "~{\"name\": \"Ortega\"}", "organization_id": null}, {"name": "Pellerin", "classification": "coauthor", "entity_type": "person", "primary": false, "person_id": "~{\"name\": \"Pellerin\"}", "organization_id": null}, {"name": "Celeste Rodriguez", "classification": "coauthor", "entity_type": "person", "primary": false, "person_id": "~{\"name\": \"Celeste Rodriguez\"}", "organization_id": null}, {"name": "Rogers", "classification": "coauthor", "entity_type": "person", "primary": false, "person_id": "~{\"name\": \"Rogers\"}", "organization_id": null}, {"name": "Sharp-Collins", "classification": "coauthor", "entity_type": "person", "primary": false, "person_id": "~{\"name\": \"Sharp-Collins\"}", "organization_id": null}], "related_bills": [], "versions": [{"note": "AB2729", "links": [{"url": "http://leginfo.legislature.ca.gov/faces/billNavClient.xhtml?bill_id=202520260AB2729", "media_type": "text/html"}], "date": "", "classification": ""}, {"note": "02/20/26 - Introduced", "links": [{"url": "https://leginfo.legislature.ca.gov/faces/billPdf.xhtml?bill_id=202520260AB2729&version=20250AB272999INT", "media_type": "application/pdf"}], "date": "2026-02-20", "classification": ""}], "documents": [], "citations": [], "sources": [{"url": "http://leginfo.legislature.ca.gov/faces/billNavClient.xhtml?bill_id=202520260AB2729", "note": ""}], "extras": {"impact_clause": "An act relating to Medi-Cal.", "tags": []}, "jurisdiction": {"id": "ocd-jurisdiction/country:us/state:ca/government", "name": "California", "classification": "state", "division_id": "ocd-division/country:us/state:ca"}, "scraped_at": "2026-02-22T08:47:44+00:00", "_id": "27e675c2-0fcb-11f1-9ce2-72e66fa16e68"}