{"legislative_session": "20252026", "identifier": "SB1359", "title": "Gas Transition Responsibility and Electrification Act.", "from_organization": "~{\"classification\": \"upper\"}", "classification": ["bill"], "subject": ["GasTransitionResponsibilityandElectrificationAct"], "abstracts": [{"note": "summary", "abstract": "The California Global Warming Solutions Act of 2006 requires the State Air Resources Board to determine what the statewide greenhouse gas emissions level was in 1990 and approve in a public hearing a statewide greenhouse gas emissions limit that is equivalent to that level, to be achieved by 2020. The act requires the state board, in adopting rules and regulations to achieve the maximum technologically feasible and cost-effective greenhouse gas emissions reductions, to ensure that the statewide greenhouse gas emissions are reduced to at least 40% below the 1990 levels no later than December 31, 2030.\n\nExisting law vests the Public Utilities Commission with regulatory authority over public utilities, including gas corporations. Existing law authorizes the commission to fix the rates and charges for every public utility and requires that those rates and charges be just and reasonable.\n\nThis bill would require the commission, before approving any capital investment by a gas corporation for natural gas distribution infrastructure exceeding $10,000,000, to determine that the proposed investment is consistent with the state's greenhouse gas emission reduction targets, and would require a gas corporation seeking approval of an investment to provide evidence regarding specified factors.\n\nUnder existing law, a violation of the Public Utilities Act or an order, decision, rule, direction, demand, or requirement of the commission is a crime.\n\nBecause the above provisions would be part of the Public Utilities Act and a violation of a commission action implementing this bill's requirements would be a crime, the bill would impose a state-mandated local program.\n\nThe California Constitution requires the state to reimburse local agencies and school districts for certain costs mandated by the state. Statutory provisions establish procedures for making that reimbursement.\n\nThis bill would provide that no reimbursement is required by this act for a specified reason."}], "other_titles": [{"note": "", "title": "Natural gas: surcharge."}], "other_identifiers": [{"identifier": "ocd-bill-ca-20252026-sb1359"}], "actions": [{"description": "Introduced. To Com. on RLS. for assignment. To print.", "date": "2026-02-20", "organization_id": "~{\"classification\": \"upper\"}", "classification": ["introduction"], "related_entities": []}, {"description": "From printer. May be acted upon on or after March 23.", "date": "2026-02-23", "organization_id": "~{\"classification\": \"upper\"}", "classification": [], "related_entities": []}, {"description": "Read first time.", "date": "2026-02-23", "organization_id": "~{\"classification\": \"upper\"}", "classification": ["reading-1"], "related_entities": []}, {"description": "Referred to Com. on RLS.", "date": "2026-03-04", "organization_id": "~{\"classification\": \"upper\"}", "classification": ["referral-committee"], "related_entities": [{"name": "Com. on RLS.", "entity_type": "organization", "organization_id": null}]}, {"description": "From committee with author's amendments. Read second time and amended. Re-referred to Com. on RLS.", "date": "2026-03-25", "organization_id": "~{\"classification\": \"upper\"}", "classification": ["amendment-passage", "committee-passage", "reading-1", "reading-2", "referral-committee"], "related_entities": [{"name": "Com. on RLS.", "entity_type": "organization", "organization_id": null}]}, {"description": "Re-referred to Com. on E., U & C.", "date": "2026-04-08", "organization_id": "~{\"classification\": \"upper\"}", "classification": ["referral-committee"], "related_entities": [{"name": "Com. on E., U & C.", "entity_type": "organization", "organization_id": null}]}, {"description": "From committee with author's amendments. Read second time and amended. Re-referred to Com. on E., U & C.", "date": "2026-04-13", "organization_id": "~{\"classification\": \"upper\"}", "classification": ["amendment-passage", "committee-passage", "reading-1", "reading-2", "referral-committee"], "related_entities": [{"name": "Com. on E., U & C.", "entity_type": "organization", "organization_id": null}]}, {"description": "Set for hearing April 21.", "date": "2026-04-16", "organization_id": "~{\"classification\": \"upper\"}", "classification": [], "related_entities": []}, {"description": "From committee: Do pass and re-refer to Com. on APPR. (Ayes 10. Noes 4.) (April 21). Re-referred to Com. on APPR.", "date": "2026-04-22", "organization_id": "~{\"classification\": \"upper\"}", "classification": ["committee-passage", "committee-passage-favorable", "referral-committee"], "related_entities": [{"name": "Com. on APPR.", "entity_type": "organization", "organization_id": null}]}, {"description": "Set for hearing May 4.", "date": "2026-04-24", "organization_id": "~{\"classification\": \"upper\"}", "classification": [], "related_entities": []}, {"description": "May 4 hearing: Placed on APPR. suspense file.", "date": "2026-05-04", "organization_id": "~{\"classification\": \"upper\"}", "classification": [], "related_entities": []}, {"description": "Set for hearing May 14.", "date": "2026-05-08", "organization_id": "~{\"classification\": \"upper\"}", "classification": [], "related_entities": []}, {"description": "From committee: Do pass as amended. (Ayes 5. Noes 2.) (May 14).", "date": "2026-05-14", "organization_id": "~{\"classification\": \"upper\"}", "classification": ["amendment-passage", "committee-passage", "committee-passage-favorable"], "related_entities": []}, {"description": "Read second time and amended. Ordered to second reading.", "date": "2026-05-14", "organization_id": "~{\"classification\": \"upper\"}", "classification": ["amendment-passage", "reading-1", "reading-2"], "related_entities": []}, {"description": "Read second time. Ordered to third reading.", "date": "2026-05-18", "organization_id": "~{\"classification\": \"upper\"}", "classification": ["reading-1", "reading-2"], "related_entities": []}], "sponsorships": [{"name": "Stern", "classification": "author", "entity_type": "person", "primary": true, "person_id": "~{\"name\": \"Stern\"}", "organization_id": null}], "related_bills": [], "versions": [{"note": "SB1359", "links": [{"url": "http://leginfo.legislature.ca.gov/faces/billNavClient.xhtml?bill_id=202520260SB1359", "media_type": "text/html"}], "date": "", "classification": ""}, {"note": "02/20/26 - Introduced", "links": [{"url": "https://leginfo.legislature.ca.gov/faces/billPdf.xhtml?bill_id=202520260SB1359&version=20250SB135999INT", "media_type": "application/pdf"}], "date": "2026-02-20", "classification": ""}, {"note": "03/25/26 - Amended Senate", "links": [{"url": "https://leginfo.legislature.ca.gov/faces/billPdf.xhtml?bill_id=202520260SB1359&version=20250SB135998AMD", "media_type": "application/pdf"}], "date": "2026-03-25", "classification": ""}, {"note": "04/13/26 - Amended Senate", "links": [{"url": "https://leginfo.legislature.ca.gov/faces/billPdf.xhtml?bill_id=202520260SB1359&version=20250SB135997AMD", "media_type": "application/pdf"}], "date": "2026-04-13", "classification": ""}, {"note": "05/14/26 - Amended Senate", "links": [{"url": "https://leginfo.legislature.ca.gov/faces/billPdf.xhtml?bill_id=202520260SB1359&version=20250SB135996AMD", "media_type": "application/pdf"}], "date": "2026-05-14", "classification": ""}], "documents": [{"note": "04/19/26- Senate Energy, Utilities and Communications", "links": [{"url": "https://leginfo.legislature.ca.gov/faces/billAnalysisClient.xhtml?bill_id=202520260SB1359&analysisId=396388&analyzingOffice=Senate+Energy,+Utilities+and+Communications", "media_type": "application/pdf"}], "date": "2026-04-19", "classification": "analysis"}, {"note": "05/01/26- Senate Appropriations", "links": [{"url": "https://leginfo.legislature.ca.gov/faces/billAnalysisClient.xhtml?bill_id=202520260SB1359&analysisId=397449&analyzingOffice=Senate+Appropriations", "media_type": "application/pdf"}], "date": "2026-05-01", "classification": "analysis"}, {"note": "05/14/26- Senate Appropriations", "links": [{"url": "https://leginfo.legislature.ca.gov/faces/billAnalysisClient.xhtml?bill_id=202520260SB1359&analysisId=398437&analyzingOffice=Senate+Appropriations", "media_type": "application/pdf"}], "date": "2026-05-14", "classification": "analysis"}, {"note": "05/18/26- Sen. Floor Analyses", "links": [{"url": "https://leginfo.legislature.ca.gov/faces/billAnalysisClient.xhtml?bill_id=202520260SB1359&analysisId=398735&analyzingOffice=Sen.+Floor+Analyses", "media_type": "application/pdf"}], "date": "2026-05-18", "classification": "analysis"}], "citations": [], "sources": [{"url": "http://leginfo.legislature.ca.gov/faces/billNavClient.xhtml?bill_id=202520260SB1359", "note": ""}], "extras": {"impact_clause": "An act to add the heading of Article 1 (commencing with Section 328) to, and to add Article 2 (commencing with Section 329) to, Chapter 2.2 of Part 1 of Division 1 of the Public Utilities Code, relating to natural gas.", "tags": ["fiscal committee", "local program"]}, "jurisdiction": {"id": "ocd-jurisdiction/country:us/state:ca/government", "name": "California", "classification": "state", "division_id": "ocd-division/country:us/state:ca"}, "scraped_at": "2026-05-20T11:06:15+00:00", "_id": "eb4cd24a-543b-11f1-814f-4a9f77784668"}