{"legislative_session": "20252026", "identifier": "AB2005", "title": "Housing developments: urban lot split: owner-occupancy.", "from_organization": "~{\"classification\": \"lower\"}", "classification": ["bill"], "subject": ["Housingdevelopments", "owner-occupancy", "urbanlotsplit"], "abstracts": [{"note": "summary", "abstract": "Under the Planning and Zoning Law, the legislative body of a city or county may adopt ordinances that, among other things, regulate the use of buildings, structures, and land, as provided. The Subdivision Map Act vests the authority to regulate and control the design and improvement of subdivisions in the legislative body of a local agency and sets forth procedures governing the local agency's processing, approval, conditional approval or disapproval, and filing of tentative, final, and parcel maps.\n\nExisting law requires a local agency to ministerially approve a parcel map for an urban lot split if the development or parcel meets specified requirements. Existing law requires the local agency to require an applicant for an urban lot split to sign an affidavit stating that the applicant intends to occupy one of the housing units as their principal residence for a minimum of 3 years from the date of the approval of the urban lot split. Existing law authorizes a local agency to adopt an ordinance to implement these provisions, as provided.\n\nThis bill would require the local agency to require an applicant to either sign the above-described affidavit requiring owner-occupancy or for the applicant to require, as a condition of sale to a homebuyer, that one of the units on both parcels of an urban lot split remain owner occupied for 3 years, beginning on the date a parcel or unit is conveyed by the applicant to a homebuyer. By increasing the duties of local agencies, the bill would impose a state-mandated local program.\n\nThis bill would impose prescribed recording and notice requirements on this 2nd owner-occupancy requirement, as provided. The bill would provide that, for the purposes of either owner-occupancy requirement, an applicant may be the managing or authorized member of a limited liability company or the trustee of a living trust.\n\nThis bill would additionally prohibit a local agency from adopting or imposing any requirement, process, practice, or procedure, or undertaking any course of conduct, that applies to a project solely or partially on the basis that the project is an urban lot split, including, but not limited to, restricting the eligibility of an applicant of an urban lot split.\n\nExisting law requires that specified disclosures be made upon any transfer by sale, exchange, real property sales contract, lease with an option to purchase, any other option to purchase, or ground lease coupled with improvements, of any single-family residential property.\n\nThis bill would require the seller of an urban lot split subject to the second owner-occupancy requirement described above to disclose, in writing, any owner-occupancy requirement for three years after the conveyance of an urban lot split unit.\n\nThe California Constitution requires the state to reimburse local agencies and school districts for certain costs mandated by the state. Statutory provisions establish procedures for making that reimbursement.\n\nThis bill would provide that no reimbursement is required by this act for a specified reason."}], "other_titles": [{"note": "", "title": "Housing developments: urban lot split: parcel maps."}], "other_identifiers": [{"identifier": "ocd-bill-ca-20252026-ab2005"}], "actions": [{"description": "Read first time. To print.", "date": "2026-02-17", "organization_id": "~{\"classification\": \"lower\"}", "classification": ["reading-1"], "related_entities": []}, {"description": "From printer. May be heard in committee March 20.", "date": "2026-02-18", "organization_id": "~{\"classification\": \"lower\"}", "classification": [], "related_entities": []}, {"description": "Referred to Coms. on H. & C.D. and L. GOV.", "date": "2026-03-19", "organization_id": "~{\"classification\": \"lower\"}", "classification": ["referral-committee"], "related_entities": [{"name": "Coms. on H. & C.D. and L. GOV.", "entity_type": "organization", "organization_id": null}]}, {"description": "From committee chair, with author's amendments: Amend, and re-refer to Com. on H. & C.D. Read second time and amended.", "date": "2026-03-19", "organization_id": "~{\"classification\": \"lower\"}", "classification": ["amendment-introduction", "amendment-passage", "reading-1", "reading-2"], "related_entities": []}, {"description": "Re-referred to Com. on H. & C.D.", "date": "2026-03-23", "organization_id": "~{\"classification\": \"lower\"}", "classification": ["referral-committee"], "related_entities": [{"name": "Com. on H. & C.D.", "entity_type": "organization", "organization_id": null}]}, {"description": "From committee: Amend, and do pass as amended and re-refer to Com. on L. GOV. (Ayes 11. Noes 0.) (April 8).", "date": "2026-04-08", "organization_id": "~{\"classification\": \"lower\"}", "classification": ["amendment-introduction", "amendment-passage", "committee-passage", "referral-committee"], "related_entities": []}, {"description": "Read second time and amended.", "date": "2026-04-09", "organization_id": "~{\"classification\": \"lower\"}", "classification": ["amendment-passage", "reading-1", "reading-2"], "related_entities": []}, {"description": "Re-referred to Com. on L. GOV.", "date": "2026-04-13", "organization_id": "~{\"classification\": \"lower\"}", "classification": ["referral-committee"], "related_entities": [{"name": "Com. on L. GOV.", "entity_type": "organization", "organization_id": null}]}], "sponsorships": [{"name": "Ahrens", "classification": "author", "entity_type": "person", "primary": true, "person_id": "~{\"name\": \"Ahrens\"}", "organization_id": null}], "related_bills": [], "versions": [{"note": "AB2005", "links": [{"url": "http://leginfo.legislature.ca.gov/faces/billNavClient.xhtml?bill_id=202520260AB2005", "media_type": "text/html"}], "date": "", "classification": ""}, {"note": "02/17/26 - Introduced", "links": [{"url": "https://leginfo.legislature.ca.gov/faces/billPdf.xhtml?bill_id=202520260AB2005&version=20250AB200599INT", "media_type": "application/pdf"}], "date": "2026-02-17", "classification": ""}, {"note": "03/19/26 - Amended Assembly", "links": [{"url": "https://leginfo.legislature.ca.gov/faces/billPdf.xhtml?bill_id=202520260AB2005&version=20250AB200598AMD", "media_type": "application/pdf"}], "date": "2026-03-19", "classification": ""}, {"note": "04/09/26 - Amended Assembly", "links": [{"url": "https://leginfo.legislature.ca.gov/faces/billPdf.xhtml?bill_id=202520260AB2005&version=20250AB200597AMD", "media_type": "application/pdf"}], "date": "2026-04-09", "classification": ""}], "documents": [{"note": "04/06/26- Assembly Housing and Community Development", "links": [{"url": "https://leginfo.legislature.ca.gov/faces/billAnalysisClient.xhtml?bill_id=202520260AB2005&analysisId=395142&analyzingOffice=Assembly+Housing+and+Community+Development", "media_type": "application/pdf"}], "date": "2026-04-06", "classification": "analysis"}], "citations": [], "sources": [{"url": "http://leginfo.legislature.ca.gov/faces/billNavClient.xhtml?bill_id=202520260AB2005", "note": ""}], "extras": {"impact_clause": "An act to amend Section 66411.7 of the Government Code, and to add Section 1102.6l to the Civil Code, relating to land use.", "tags": ["fiscal committee", "local program"]}, "jurisdiction": {"id": "ocd-jurisdiction/country:us/state:ca/government", "name": "California", "classification": "state", "division_id": "ocd-division/country:us/state:ca"}, "scraped_at": "2026-04-20T10:12:52+00:00", "_id": "7de9f34c-3ca1-11f1-ba42-1e1218bee2a9"}