{"legislative_session": "20252026", "identifier": "AB1772", "title": "Fish and wildlife: aquatic invasive species: golden mussels.", "from_organization": "~{\"classification\": \"lower\"}", "classification": ["bill"], "subject": ["Fishandwildlife", "aquaticinvasivespecies", "goldenmussels"], "abstracts": [{"note": "summary", "abstract": "Existing law generally prohibits a person from possessing, importing, shipping, or transporting in the state, or from placing, planting, or causing to be placed or planted in any water within the state, invasive mussels and authorizes the Director of Fish and Wildlife or the director's designee to engage in various enforcement activities with regard to invasive mussels, as provided. Existing law requires specified entities that own or manage a reservoir, as defined, where certain activities are permitted to monitor and prevent the introduction of invasive mussel species, as specified, and requires any entity that discovers invasive mussels in the state to report the discovery immediately to the department.\n\nThis bill would provide that it is the intent of the Legislature to enact subsequent legislation to, among other things, address and prevent the spread of aquatic invasive species, including, but not limited to, the golden mussel, in California's waterbodies and water infrastructure systems. The bill would also make various findings and declarations relating to aquatic invasive species."}], "other_titles": [], "other_identifiers": [], "actions": [{"description": "Read first time. To print.", "date": "2026-02-09", "organization_id": "~{\"classification\": \"lower\"}", "classification": ["reading-1"], "related_entities": []}, {"description": "From printer. May be heard in committee March 12.", "date": "2026-02-10", "organization_id": "~{\"classification\": \"lower\"}", "classification": [], "related_entities": []}], "sponsorships": [{"name": "Papan", "classification": "author", "entity_type": "person", "primary": true, "person_id": "~{\"name\": \"Papan\"}", "organization_id": null}, {"name": "Bains", "classification": "coauthor", "entity_type": "person", "primary": false, "person_id": "~{\"name\": \"Bains\"}", "organization_id": null}, {"name": "Boerner", "classification": "coauthor", "entity_type": "person", "primary": false, "person_id": "~{\"name\": \"Boerner\"}", "organization_id": null}, {"name": "Caloza", "classification": "coauthor", "entity_type": "person", "primary": false, "person_id": "~{\"name\": \"Caloza\"}", "organization_id": null}, {"name": "Gallagher", "classification": "coauthor", "entity_type": "person", "primary": false, "person_id": "~{\"name\": \"Gallagher\"}", "organization_id": null}, {"name": "Jeff Gonzalez", "classification": "coauthor", "entity_type": "person", "primary": false, "person_id": "~{\"name\": \"Jeff Gonzalez\"}", "organization_id": null}, {"name": "Hart", "classification": "coauthor", "entity_type": "person", "primary": false, "person_id": "~{\"name\": \"Hart\"}", "organization_id": null}, {"name": "Ransom", "classification": "coauthor", "entity_type": "person", "primary": false, "person_id": "~{\"name\": \"Ransom\"}", "organization_id": null}, {"name": "Celeste Rodriguez", "classification": "coauthor", "entity_type": "person", "primary": false, "person_id": "~{\"name\": \"Celeste Rodriguez\"}", "organization_id": null}, {"name": "Rogers", "classification": "coauthor", "entity_type": "person", "primary": false, "person_id": "~{\"name\": \"Rogers\"}", "organization_id": null}, {"name": "Blanca Rubio", "classification": "coauthor", "entity_type": "person", "primary": false, "person_id": "~{\"name\": \"Blanca Rubio\"}", "organization_id": null}], "related_bills": [], "versions": [{"note": "AB1772", "links": [{"url": "http://leginfo.legislature.ca.gov/faces/billNavClient.xhtml?bill_id=202520260AB1772", "media_type": "text/html"}], "date": "", "classification": ""}, {"note": "02/09/26 - Introduced", "links": [{"url": "https://leginfo.legislature.ca.gov/faces/billPdf.xhtml?bill_id=202520260AB1772&version=20250AB177299INT", "media_type": "application/pdf"}], "date": "2026-02-09", "classification": ""}], "documents": [], "citations": [], "sources": [{"url": "http://leginfo.legislature.ca.gov/faces/billNavClient.xhtml?bill_id=202520260AB1772", "note": ""}], "extras": {"impact_clause": "An act relating to fish and wildlife.", "tags": []}, "jurisdiction": {"id": "ocd-jurisdiction/country:us/state:ca/government", "name": "California", "classification": "state", "division_id": "ocd-division/country:us/state:ca"}, "scraped_at": "2026-02-19T09:00:56+00:00", "_id": "808df184-0d71-11f1-814c-2ab210762532"}