{"legislative_session": "20252026", "identifier": "HR105", "title": "Relative to Amyotrophic Lateral Sclerosis Awareness Month.", "from_organization": "~{\"classification\": \"lower\"}", "classification": ["resolution"], "subject": [], "abstracts": [], "other_titles": [], "other_identifiers": [{"identifier": "ocd-bill-ca-20252026-hr105"}], "actions": [{"description": "Introduced.", "date": "2026-04-13", "organization_id": "~{\"classification\": \"lower\"}", "classification": ["introduction"], "related_entities": []}], "sponsorships": [{"name": "Boerner", "classification": "coauthor", "entity_type": "person", "primary": false, "person_id": "~{\"name\": \"Boerner\"}", "organization_id": null}, {"name": "Zbur", "classification": "author", "entity_type": "person", "primary": true, "person_id": "~{\"name\": \"Zbur\"}", "organization_id": null}, {"name": "Alanis", "classification": "coauthor", "entity_type": "person", "primary": false, "person_id": "~{\"name\": \"Alanis\"}", "organization_id": null}, {"name": "Dixon", "classification": "coauthor", "entity_type": "person", "primary": false, "person_id": "~{\"name\": \"Dixon\"}", "organization_id": null}, {"name": "Jeff Gonzalez", "classification": "coauthor", "entity_type": "person", "primary": false, "person_id": "~{\"name\": \"Jeff Gonzalez\"}", "organization_id": null}, {"name": "Papan", "classification": "coauthor", "entity_type": "person", "primary": false, "person_id": "~{\"name\": \"Papan\"}", "organization_id": null}, {"name": "Ransom", "classification": "coauthor", "entity_type": "person", "primary": false, "person_id": "~{\"name\": \"Ransom\"}", "organization_id": null}, {"name": "Ward", "classification": "coauthor", "entity_type": "person", "primary": false, "person_id": "~{\"name\": \"Ward\"}", "organization_id": null}], "related_bills": [], "versions": [{"note": "HR105", "links": [{"url": "http://leginfo.legislature.ca.gov/faces/billNavClient.xhtml?bill_id=202520260HR105", "media_type": "text/html"}], "date": "", "classification": ""}, {"note": "04/13/26 - Introduced", "links": [{"url": "https://leginfo.legislature.ca.gov/faces/billPdf.xhtml?bill_id=202520260HR105&version=20250HR10599INT", "media_type": "application/pdf"}], "date": "2026-04-13", "classification": ""}], "documents": [], "citations": [], "sources": [{"url": "http://leginfo.legislature.ca.gov/faces/billNavClient.xhtml?bill_id=202520260HR105", "note": ""}], "extras": {"impact_clause": null, "tags": []}, "jurisdiction": {"id": "ocd-jurisdiction/country:us/state:ca/government", "name": "California", "classification": "state", "division_id": "ocd-division/country:us/state:ca"}, "scraped_at": "2026-04-16T09:37:28+00:00", "_id": "e249288a-3977-11f1-be0c-a6f909cf49a0"}