{"legislative_session": "20252026", "identifier": "AB2760", "title": "Educational equity: discrimination: Office of Civil Rights.", "from_organization": "~{\"classification\": \"lower\"}", "classification": ["bill"], "subject": ["Educationalequity", "OfficeofCivilRights", "discrimination"], "abstracts": [{"note": "summary", "abstract": "Existing law establishes the Office of Civil Rights, under the administration of the Government Operations Agency, with the purpose of working directly with school districts, county offices of education, and charter schools to prevent and address discrimination and bias, as described. Existing law requires the office to engage with and seek advice from specified coordinators on actions implemented by the office.\n\nThis bill would make nonsubstantive changes to the latter provision."}], "other_titles": [], "other_identifiers": [], "actions": [{"description": "Read first time. To print.", "date": "2026-02-20", "organization_id": "~{\"classification\": \"lower\"}", "classification": ["reading-1"], "related_entities": []}], "sponsorships": [{"name": "Sharp-Collins", "classification": "author", "entity_type": "person", "primary": true, "person_id": "~{\"name\": \"Sharp-Collins\"}", "organization_id": null}], "related_bills": [], "versions": [{"note": "AB2760", "links": [{"url": "http://leginfo.legislature.ca.gov/faces/billNavClient.xhtml?bill_id=202520260AB2760", "media_type": "text/html"}], "date": "", "classification": ""}, {"note": "02/20/26 - Introduced", "links": [{"url": "https://leginfo.legislature.ca.gov/faces/billPdf.xhtml?bill_id=202520260AB2760&version=20250AB276099INT", "media_type": "application/pdf"}], "date": "2026-02-20", "classification": ""}], "documents": [], "citations": [], "sources": [{"url": "http://leginfo.legislature.ca.gov/faces/billNavClient.xhtml?bill_id=202520260AB2760", "note": ""}], "extras": {"impact_clause": "An act to amend Section 33801 of the Education Code, relating to education.", "tags": []}, "jurisdiction": {"id": "ocd-jurisdiction/country:us/state:ca/government", "name": "California", "classification": "state", "division_id": "ocd-division/country:us/state:ca"}, "scraped_at": "2026-02-22T08:47:45+00:00", "_id": "2851397a-0fcb-11f1-9ce2-72e66fa16e68"}