{"legislative_session": "20252026", "identifier": "AB1891", "title": "Forestry: Beneficial Fire Capacity Program.", "from_organization": "~{\"classification\": \"lower\"}", "classification": ["bill"], "subject": ["BeneficialFireCapacityProgram", "Forestry"], "abstracts": [{"note": "summary", "abstract": "Existing law authorizes a person that owns or controls brush-covered land, forest lands, woodland, grassland, and shrubland within a state responsibility area to apply to the Department of Forestry and Fire Protection for permission to use prescribed burning for certain public purposes. Existing law authorizes the Director of Forestry and Fire Protection to enter into an agreement for prescribed burning with a person to conduct the prescribed burning operations for certain purposes. Existing law requires the department to develop a training program for prescribed fire users to certify professionals as burn bosses. Existing law requires the department to conduct an experimental program of wildland resources management through prescribed burning and other methods in 2 areas of wildlands. \n\nThis bill would establish in the department the Beneficial Fire Capacity Program to expand training, organizational capacity, and support for community-led beneficial fire programs, including those developed by California Native American tribes, nongovernmental organizations, universities and colleges, resources conservation districts, volunteer fire districts, and other local or special districts, and would require the program to provide competitive grants for beneficial fire implementation, capacity building, research, innovation, and training. The bill would require the department to take certain actions to maximize the benefits of the program. The bill would require the department to publish and update on its internet website certain information related to implementation of the program."}], "other_titles": [], "other_identifiers": [], "actions": [{"description": "Read first time. To print.", "date": "2026-02-12", "organization_id": "~{\"classification\": \"lower\"}", "classification": ["reading-1"], "related_entities": []}, {"description": "From printer. May be heard in committee March 15.", "date": "2026-02-13", "organization_id": "~{\"classification\": \"lower\"}", "classification": [], "related_entities": []}], "sponsorships": [{"name": "Connolly", "classification": "author", "entity_type": "person", "primary": true, "person_id": "~{\"name\": \"Connolly\"}", "organization_id": null}, {"name": "Rogers", "classification": "coauthor", "entity_type": "person", "primary": false, "person_id": "~{\"name\": \"Rogers\"}", "organization_id": null}], "related_bills": [], "versions": [{"note": "AB1891", "links": [{"url": "http://leginfo.legislature.ca.gov/faces/billNavClient.xhtml?bill_id=202520260AB1891", "media_type": "text/html"}], "date": "", "classification": ""}, {"note": "02/12/26 - Introduced", "links": [{"url": "https://leginfo.legislature.ca.gov/faces/billPdf.xhtml?bill_id=202520260AB1891&version=20250AB189199INT", "media_type": "application/pdf"}], "date": "2026-02-12", "classification": ""}], "documents": [], "citations": [], "sources": [{"url": "http://leginfo.legislature.ca.gov/faces/billNavClient.xhtml?bill_id=202520260AB1891", "note": ""}], "extras": {"impact_clause": "An act to add Chapter 6.5 (commencing with Section 4450) to Part 2 of Division 4 of the Public Resources Code, relating to forestry.", "tags": ["fiscal committee"]}, "jurisdiction": {"id": "ocd-jurisdiction/country:us/state:ca/government", "name": "California", "classification": "state", "division_id": "ocd-division/country:us/state:ca"}, "scraped_at": "2026-02-20T08:57:54+00:00", "_id": "3ebe0c8e-0e3a-11f1-a618-2a6200350f1a"}