{"legislative_session": "20252026", "identifier": "AB2254", "title": "Coastal resources: local coastal program: monarch butterfly habitat.", "from_organization": "~{\"classification\": \"lower\"}", "classification": ["bill"], "subject": ["Coastalresources", "localcoastalprogram", "monarchbutterflyhabitat"], "abstracts": [{"note": "summary", "abstract": "Existing law establishes the Department of Fish and Wildlife and sets forth the duties of that department, which include administering various programs for the protection and conservation of fish and wildlife. Existing law authorizes the department to take feasible actions to conserve monarch butterflies and the unique habitats they depend upon for successful migration.\n\nExisting law, the California Coastal Act of 1976, among other things, establishes the California Coastal Commission and provides for planning and regulation of development in the coastal zone, as defined. The act requires the commission to adopt, after public hearing, procedures for the preparation, submission, approval, appeal, certification, and amendment of a local coastal program, as provided. The act generally requires each local government, as specified, to prepare a local coastal program for certification by the commission.\n\nThis bill would require, on or before January 1, 2028, the department, in coordination with the commission, to identify monarch butterfly overwintering habitat sites in the coastal zone and current local government monarch butterfly overwintering habitat management plans or policies. The bill would also require, on or before July 1, 2028, the department, in coordination with the commission, to develop and provide guidance on model policies to be used by a local government for the protection of monarch butterfly overwintering habitat, including habitat restoration and enhancement. The bill would require, after the above-described guidance on model policies is finalized, a local government with a monarch butterfly overwintering habitat site located within their jurisdiction and the coastal zone, as described, at the time of their next amendment to their local coastal program, to include monarch butterfly overwintering habitat site protection policies in their local coastal program. By imposing additional duties on a local government, the bill would impose a state-mandated local program.\n\nThe California Constitution requires the state to reimburse local agencies and school districts for certain costs mandated by the state. Statutory provisions establish procedures for making that reimbursement.\n\nThis bill would provide that, if the Commission on State Mandates determines that the bill contains costs mandated by the state, reimbursement for those costs shall be made pursuant to the statutory provisions noted above."}], "other_titles": [{"note": "", "title": "Monarch butterflies: conservation."}], "other_identifiers": [{"identifier": "ocd-bill-ca-20252026-ab2254"}], "actions": [{"description": "Read first time. To print.", "date": "2026-02-19", "organization_id": "~{\"classification\": \"lower\"}", "classification": ["reading-1"], "related_entities": []}, {"description": "From printer. May be heard in committee March 22.", "date": "2026-02-20", "organization_id": "~{\"classification\": \"lower\"}", "classification": [], "related_entities": []}, {"description": "Referred to Coms. on NAT. RES. and W., P., & W.", "date": "2026-03-16", "organization_id": "~{\"classification\": \"lower\"}", "classification": ["referral-committee"], "related_entities": [{"name": "Coms. on NAT. RES. and W., P., & W.", "entity_type": "organization", "organization_id": null}]}, {"description": "From committee chair, with author's amendments: Amend, and re-refer to Com. on NAT. RES. Read second time and amended.", "date": "2026-03-16", "organization_id": "~{\"classification\": \"lower\"}", "classification": ["amendment-introduction", "amendment-passage", "reading-1", "reading-2"], "related_entities": []}, {"description": "Re-referred to Com. on NAT. RES.", "date": "2026-03-17", "organization_id": "~{\"classification\": \"lower\"}", "classification": ["referral-committee"], "related_entities": [{"name": "Com. on NAT. RES.", "entity_type": "organization", "organization_id": null}]}, {"description": "From committee: Amend, and do pass as amended and re-refer to Com. on W., P., & W. (Ayes 10. Noes 3.) (April 6).", "date": "2026-04-07", "organization_id": "~{\"classification\": \"lower\"}", "classification": ["amendment-introduction", "amendment-passage", "committee-passage", "referral-committee"], "related_entities": []}, {"description": "Read second time and amended.", "date": "2026-04-08", "organization_id": "~{\"classification\": \"lower\"}", "classification": ["amendment-passage", "reading-1", "reading-2"], "related_entities": []}, {"description": "Re-referred to Com. on W., P., & W.", "date": "2026-04-09", "organization_id": "~{\"classification\": \"lower\"}", "classification": ["referral-committee"], "related_entities": [{"name": "Com. on W., P., & W.", "entity_type": "organization", "organization_id": null}]}, {"description": "Coauthors revised.", "date": "2026-04-15", "organization_id": "~{\"classification\": \"lower\"}", "classification": [], "related_entities": []}, {"description": "From committee: Do pass and re-refer to Com. on APPR. (Ayes 10. Noes 2.) (April 14). Re-referred to Com. on APPR.", "date": "2026-04-15", "organization_id": "~{\"classification\": \"lower\"}", "classification": ["committee-passage", "committee-passage-favorable", "referral-committee"], "related_entities": [{"name": "Com. on APPR.", "entity_type": "organization", "organization_id": null}]}, {"description": "In committee: Set, first hearing. Referred to APPR. suspense file.", "date": "2026-05-06", "organization_id": "~{\"classification\": \"lower\"}", "classification": ["referral-committee"], "related_entities": [{"name": "APPR. suspense file.", "entity_type": "organization", "organization_id": null}, {"name": "APPR", "entity_type": "organization", "organization_id": null}]}], "sponsorships": [{"name": "Addis", "classification": "author", "entity_type": "person", "primary": true, "person_id": "~{\"name\": \"Addis\"}", "organization_id": null}, {"name": "Zbur", "classification": "coauthor", "entity_type": "person", "primary": false, "person_id": "~{\"name\": \"Zbur\"}", "organization_id": null}, {"name": "Hart", "classification": "coauthor", "entity_type": "person", "primary": false, "person_id": "~{\"name\": \"Hart\"}", "organization_id": null}], "related_bills": [], "versions": [{"note": "AB2254", "links": [{"url": "http://leginfo.legislature.ca.gov/faces/billNavClient.xhtml?bill_id=202520260AB2254", "media_type": "text/html"}], "date": "", "classification": ""}, {"note": "02/19/26 - Introduced", "links": [{"url": "https://leginfo.legislature.ca.gov/faces/billPdf.xhtml?bill_id=202520260AB2254&version=20250AB225499INT", "media_type": "application/pdf"}], "date": "2026-02-19", "classification": ""}, {"note": "03/16/26 - Amended Assembly", "links": [{"url": "https://leginfo.legislature.ca.gov/faces/billPdf.xhtml?bill_id=202520260AB2254&version=20250AB225498AMD", "media_type": "application/pdf"}], "date": "2026-03-16", "classification": ""}, {"note": "04/08/26 - Amended Assembly", "links": [{"url": "https://leginfo.legislature.ca.gov/faces/billPdf.xhtml?bill_id=202520260AB2254&version=20250AB225497AMD", "media_type": "application/pdf"}], "date": "2026-04-08", "classification": ""}], "documents": [{"note": "04/03/26- Assembly Natural Resources", "links": [{"url": "https://leginfo.legislature.ca.gov/faces/billAnalysisClient.xhtml?bill_id=202520260AB2254&analysisId=394833&analyzingOffice=Assembly+Natural+Resources", "media_type": "application/pdf"}], "date": "2026-04-03", "classification": "analysis"}, {"note": "04/10/26- Assembly Water, Parks and Wildlife", "links": [{"url": "https://leginfo.legislature.ca.gov/faces/billAnalysisClient.xhtml?bill_id=202520260AB2254&analysisId=395450&analyzingOffice=Assembly+Water,+Parks+and+Wildlife", "media_type": "application/pdf"}], "date": "2026-04-10", "classification": "analysis"}, {"note": "05/05/26- Assembly Appropriations", "links": [{"url": "https://leginfo.legislature.ca.gov/faces/billAnalysisClient.xhtml?bill_id=202520260AB2254&analysisId=397704&analyzingOffice=Assembly+Appropriations", "media_type": "application/pdf"}], "date": "2026-05-05", "classification": "analysis"}], "citations": [], "sources": [{"url": "http://leginfo.legislature.ca.gov/faces/billNavClient.xhtml?bill_id=202520260AB2254", "note": ""}], "extras": {"impact_clause": "An act to add Section 1021.5 to the Fish and Game Code, and to add Section 30505 to the Public Resources Code, relating to coastal resources.", "tags": ["fiscal committee", "local program"]}, "jurisdiction": {"id": "ocd-jurisdiction/country:us/state:ca/government", "name": "California", "classification": "state", "division_id": "ocd-division/country:us/state:ca"}, "scraped_at": "2026-05-11T11:38:12+00:00", "_id": "e43c13b8-4d2d-11f1-ab0a-9ab8b26d47ac"}