{"legislative_session": "20252026", "identifier": "SB1128", "title": "Pupils: technology-based materials: school-issued electronic devices.", "from_organization": "~{\"classification\": \"upper\"}", "classification": ["bill"], "subject": ["Pupils", "school-issuedelectronicdevices", "technology-basedmaterials"], "abstracts": [{"note": "summary", "abstract": "Existing law authorizes the governing board of a school district, when adopting instructional materials for use in school, to include relevant technology-based materials, defined for these purposes to mean basic or supplemental instructional materials that are designed for use by pupils and teachers as learning resources and that require the availability of electronic equipment in order to be used as a learning resource, and including the electronic equipment required to make use of those materials used by pupils and teachers as a learning resource, including, but not limited to, laptop computers and devices that provide internet access. Existing law prohibits a school official from requiring a pupil to purchase any instructional materials for the pupil's use in the school, except as provided.\n\nCommencing with the 2027\u201328 school year, this bill would prohibit a school district, county office of education, or charter school from requiring a pupil in kindergarten, including a pupil in transitional kindergarten, to take home a school-issued electronic device, as defined, except that a local educational agency may authorize those pupils to take home a school-issued electronic device.\n\n This bill would require the State Department of Education, on or before July 1, 2027, to develop and post on its internet website model policies for the age-appropriate use of school-issued electronic devices in school and to take into consideration when developing those policies, among other things, developmentally appropriate screen exposure time."}], "other_titles": [{"note": "", "title": "Pupils: use of social media."}], "other_identifiers": [{"identifier": "ocd-bill-ca-20252026-sb1128"}], "actions": [{"description": "Introduced. Read first time. To Com. on RLS. for assignment. To print.", "date": "2026-02-17", "organization_id": "~{\"classification\": \"upper\"}", "classification": ["introduction", "reading-1"], "related_entities": []}, {"description": "From printer. May be acted upon on or after March 20.", "date": "2026-02-18", "organization_id": "~{\"classification\": \"upper\"}", "classification": [], "related_entities": []}, {"description": "Referred to Com. on ED.", "date": "2026-02-26", "organization_id": "~{\"classification\": \"upper\"}", "classification": ["referral-committee"], "related_entities": [{"name": "Com. on ED.", "entity_type": "organization", "organization_id": null}]}, {"description": "Set for hearing April 22.", "date": "2026-04-10", "organization_id": "~{\"classification\": \"upper\"}", "classification": [], "related_entities": []}, {"description": "From committee with author's amendments. Read second time and amended. Re-referred to Com. on ED.", "date": "2026-04-14", "organization_id": "~{\"classification\": \"upper\"}", "classification": ["amendment-passage", "committee-passage", "reading-1", "reading-2", "referral-committee"], "related_entities": [{"name": "Com. on ED.", "entity_type": "organization", "organization_id": null}]}], "sponsorships": [{"name": "Stern", "classification": "author", "entity_type": "person", "primary": true, "person_id": "~{\"name\": \"Stern\"}", "organization_id": null}], "related_bills": [], "versions": [{"note": "SB1128", "links": [{"url": "http://leginfo.legislature.ca.gov/faces/billNavClient.xhtml?bill_id=202520260SB1128", "media_type": "text/html"}], "date": "", "classification": ""}, {"note": "02/17/26 - Introduced", "links": [{"url": "https://leginfo.legislature.ca.gov/faces/billPdf.xhtml?bill_id=202520260SB1128&version=20250SB112899INT", "media_type": "application/pdf"}], "date": "2026-02-17", "classification": ""}, {"note": "04/14/26 - Amended Senate", "links": [{"url": "https://leginfo.legislature.ca.gov/faces/billPdf.xhtml?bill_id=202520260SB1128&version=20250SB112898AMD", "media_type": "application/pdf"}], "date": "2026-04-14", "classification": ""}], "documents": [], "citations": [], "sources": [{"url": "http://leginfo.legislature.ca.gov/faces/billNavClient.xhtml?bill_id=202520260SB1128", "note": ""}], "extras": {"impact_clause": "An act to add Section 60077 to the Education Code, relating to pupils.", "tags": ["fiscal committee"]}, "jurisdiction": {"id": "ocd-jurisdiction/country:us/state:ca/government", "name": "California", "classification": "state", "division_id": "ocd-division/country:us/state:ca"}, "scraped_at": "2026-04-20T10:11:37+00:00", "_id": "50f04288-3ca1-11f1-ba42-1e1218bee2a9"}