{"identifier": "", "motion_text": "Do pass as amended and be re-referred to the Committee on [Appropriations]", "motion_classification": [], "start_date": "2025-04-07T07:00:00+00:00", "result": "pass", "organization": "~{\"classification\": \"lower\"}", "legislative_session": "20252026", "bill": "fc0a4040-e492-11f0-8217-9aa9a5857dfc", "bill_action": null, "bill_identifier": "AB703", "votes": [{"option": "yes", "voter_name": "Bains", "voter_id": "~{\"name\": \"Bains\"}", "note": ""}, {"option": "yes", "voter_name": "DeMaio", "voter_id": "~{\"name\": \"DeMaio\"}", "note": ""}, {"option": "yes", "voter_name": "McKinnor", "voter_id": "~{\"name\": \"McKinnor\"}", "note": ""}, {"option": "yes", "voter_name": "Garcia", "voter_id": "~{\"name\": \"Garcia\"}", "note": ""}, {"option": "yes", "voter_name": "Gipson", "voter_id": "~{\"name\": \"Gipson\"}", "note": ""}, {"option": "yes", "voter_name": "Quirk-Silva", "voter_id": "~{\"name\": \"Quirk-Silva\"}", "note": ""}, {"option": "other", "voter_name": "Ta", "voter_id": "~{\"name\": \"Ta\"}", "note": ""}], "counts": [{"option": "yes", "value": 6}, {"option": "no", "value": 0}, {"option": "other", "value": 1}], "sources": [{"url": "http://leginfo.legislature.ca.gov/faces/billVotesClient.xhtml?bill_id=202520260AB703", "note": ""}], "extras": {"threshold": "1/2"}, "dedupe_key": "http://leginfo.legislature.ca.gov/faces/billVotesClient.xhtml?bill_id=202520260AB703#0", "_id": "fc0bc71c-e492-11f0-8217-9aa9a5857dfc"}